odoo/addons/ssi_mail_telegram/README.rst
odoo/addons/ssi_mail_telegram/__init__.py
odoo/addons/ssi_mail_telegram/__manifest__.py
odoo/addons/ssi_mail_telegram/models/__init__.py
odoo/addons/ssi_mail_telegram/models/mail_message.py
odoo/addons/ssi_mail_telegram/models/mail_message_telegram.py
odoo/addons/ssi_mail_telegram/security/ir.model.access.csv
odoo/addons/ssi_mail_telegram/static/description/icon.png
odoo/addons/ssi_mail_telegram/static/src/components/mail_telegram.js
odoo/addons/ssi_mail_telegram/static/src/components/mail_telegram.scss
odoo/addons/ssi_mail_telegram/static/src/components/mail_telegram.xml
odoo/addons/ssi_mail_telegram/static/src/components/mail_telegram_loader.js
odoo/addons/ssi_mail_telegram/views/assets.xml
odoo/addons/ssi_mail_telegram/views/mail_message_views.xml
odoo/addons/ssi_mail_telegram/wizards/__init__.py
odoo/addons/ssi_mail_telegram/wizards/send_telegram.py
odoo/addons/ssi_mail_telegram/wizards/send_telegram.xml
odoo14_addon_ssi_mail_telegram-14.0.1.2.0.dist-info/METADATA
odoo14_addon_ssi_mail_telegram-14.0.1.2.0.dist-info/WHEEL
odoo14_addon_ssi_mail_telegram-14.0.1.2.0.dist-info/top_level.txt
odoo14_addon_ssi_mail_telegram-14.0.1.2.0.dist-info/RECORD
